regexparser.py
regexparser-0.1.0.dist-info/LICENSE
regexparser-0.1.0.dist-info/WHEEL
regexparser-0.1.0.dist-info/METADATA
regexparser-0.1.0.dist-info/RECORD
